qiskit_quantuminspire/__init__.py
qiskit_quantuminspire/base_provider.py
qiskit_quantuminspire/cqasm.py
qiskit_quantuminspire/hybrid/__init__.py
qiskit_quantuminspire/hybrid/hybrid_backend.py
qiskit_quantuminspire/hybrid/hybrid_job.py
qiskit_quantuminspire/mapping/__init__.py
qiskit_quantuminspire/mapping/instruction_mapping.py
qiskit_quantuminspire/qi_backend.py
qiskit_quantuminspire/qi_instructions.py
qiskit_quantuminspire/qi_jobs.py
qiskit_quantuminspire/qi_provider.py
qiskit_quantuminspire/utils.py
qiskit_quantuminspire-0.16.0.dist-info/LICENSE
qiskit_quantuminspire-0.16.0.dist-info/METADATA
qiskit_quantuminspire-0.16.0.dist-info/WHEEL
qiskit_quantuminspire-0.16.0.dist-info/RECORD
