Metadata-Version: 2.1
Name: qiskit-quantuminspire
Version: 0.16.0
Summary: Qiskit provider for Quantum Inspire backends 
Home-page: https://www.quantum-inspire.com
Author: Quantum Inspire
Author-email: support@quantum-inspire.com
Requires-Python: >=3.10,<3.14
Classifier: Development Status :: 4 - Beta
Classifier: License :: OSI Approved :: Apache Software License
Classifier: Programming Language :: Python :: 3
Classifier: Programming Language :: Python :: 3.10
Classifier: Programming Language :: Python :: 3.11
Classifier: Programming Language :: Python :: 3.12
Classifier: Programming Language :: Python :: 3.13
Requires-Dist: colorama (>=0.4.6,<0.5.0)
Requires-Dist: opensquirrel (==0.8.0)
Requires-Dist: pydantic (>=2.10.6,<3.0.0)
Requires-Dist: qi-compute-api-client (>=0.56.0,<0.57.0)
Requires-Dist: qiskit (>=2.0.0,<2.2.0)
Requires-Dist: requests (>=2.32.3,<3.0.0)
Project-URL: Documentation, https://qutech-delft.github.io/qiskit-quantuminspire/
Project-URL: Repository, https://github.com/qutech-delft/qiskit-quantuminspire
